CHANGELOG.rst
obswebsocket_trio/__init__.py
obswebsocket_trio/base_classes.py
obswebsocket_trio/core.py
obswebsocket_trio/events.py
obswebsocket_trio/exceptions.py
obswebsocket_trio/requests.py
samples/events.py
samples/switch_scenes.py
obswebsocket_trio-0.1.1.post2.dist-info/LICENSE
obswebsocket_trio-0.1.1.post2.dist-info/WHEEL
obswebsocket_trio-0.1.1.post2.dist-info/METADATA
obswebsocket_trio-0.1.1.post2.dist-info/RECORD
